yr/datasystem/.commit_id
yr/datasystem/README.md
yr/datasystem/VERSION
yr/datasystem/__init__.py
yr/datasystem/cluster_config.json
yr/datasystem/datasystem_worker
yr/datasystem/ds_client.py
yr/datasystem/ds_tensor_client.py
yr/datasystem/dsbench_cpp
yr/datasystem/hetero_client.py
yr/datasystem/kv_client.py
yr/datasystem/object_client.py
yr/datasystem/sdk_lib_list
yr/datasystem/stream_client.py
yr/datasystem/util.py
yr/datasystem/worker_config.json
yr/datasystem/cli/__init__.py
yr/datasystem/cli/collect_log.py
yr/datasystem/cli/command.py
yr/datasystem/cli/down.py
yr/datasystem/cli/generate_config.py
yr/datasystem/cli/generate_cpp_template.py
yr/datasystem/cli/generate_helm_chart.py
yr/datasystem/cli/runscript.py
yr/datasystem/cli/start.py
yr/datasystem/cli/stop.py
yr/datasystem/cli/up.py
yr/datasystem/cli/benchmark/__init__.py
yr/datasystem/cli/benchmark/common.py
yr/datasystem/cli/benchmark/executor.py
yr/datasystem/cli/benchmark/main.py
yr/datasystem/cli/benchmark/task.py
yr/datasystem/cli/benchmark/kv/__init__.py
yr/datasystem/cli/benchmark/kv/bench_suite_builder.py
yr/datasystem/cli/benchmark/kv/bench_test_case.py
yr/datasystem/cli/benchmark/kv/command.py
yr/datasystem/cli/benchmark/kv/kv.json
yr/datasystem/cli/benchmark/kv/validator.py
yr/datasystem/cli/common/__init__.py
yr/datasystem/cli/common/constant.py
yr/datasystem/cli/common/parallel.py
yr/datasystem/cli/common/util.py
yr/datasystem/cli/cpp_template/CMakeLists.txt
yr/datasystem/cli/cpp_template/README.md
yr/datasystem/cli/cpp_template/kv_cache_example.cpp
yr/datasystem/cli/cpp_template/run.sh
yr/datasystem/cli/deploy/conf/cluster_config.json
yr/datasystem/cli/deploy/conf/worker_config.json
yr/datasystem/cpp_template/CMakeLists.txt
yr/datasystem/cpp_template/README.md
yr/datasystem/cpp_template/kv_cache_example.cpp
yr/datasystem/cpp_template/run.sh
yr/datasystem/helm_chart/datasystem/Chart.yaml
yr/datasystem/helm_chart/datasystem/values.yaml
yr/datasystem/helm_chart/datasystem/templates/configmap.yaml
openyuanrong_datasystem-0.6.3.dist-info/METADATA
openyuanrong_datasystem-0.6.3.dist-info/WHEEL
openyuanrong_datasystem-0.6.3.dist-info/entry_points.txt
openyuanrong_datasystem-0.6.3.dist-info/top_level.txt
openyuanrong_datasystem-0.6.3.dist-info/RECORD
